Metadata-Version: 1.0
Name: havij
Version: 0.6
Summary: The Havijest in the world
Home-page: http://github.com/havij
Author: EmAm
Author-email: example@example.com
License: MIT
Platform: UNKNOWN
